scanvulnpy/__init__.py
scanvulnpy/__main__.py
scanvulnpy/__version__.py
scanvulnpy/modules/__init__.py
scanvulnpy/modules/banners.py
scanvulnpy/modules/cmd.py
scanvulnpy/modules/loggers.py
scanvulnpy/modules/scanner.py
scanvulnpy/modules/utils.py
scanvulnpy-0.2.1.dist-info/LICENSE
scanvulnpy-0.2.1.dist-info/METADATA
scanvulnpy-0.2.1.dist-info/WHEEL
scanvulnpy-0.2.1.dist-info/top_level.txt
scanvulnpy-0.2.1.dist-info/RECORD
