Metadata-Version: 2.1
Name: scanvulnpy
Version: 0.2.1
Summary: A simple Package Python to scan vulnerability PyPI Packages, the data provided by https://osv.dev.
Author-email: little-scripts <jgdevrennes@gmail.com>
Maintainer-email: little-scripts <jgdevrennes@gmail.com>
License: Apache License
Project-URL: Homepage, https://github.com/little-scripts/scanvulnpy
Project-URL: Issues, https://github.com/little-scripts/scanvulnpy/issues
Project-URL: Changelog, https://github.com/little-scripts/scanvulnpy/blob/main/CHANGELOG.md
Project-URL: Funding, https://donate.pypi.org
Project-URL: Source, https://github.com/little-scripts/scanvulnpy
Classifier: Development Status :: 5 - Production/Stable
Classifier: Environment :: Console
Classifier: Intended Audience :: Developers
Classifier: License :: OSI Approved :: Apache Software License
Classifier: Topic :: Software Development :: Build Tools
Classifier: Programming Language :: Python :: 3.7
Classifier: Programming Language :: Python :: 3.8
Classifier: Programming Language :: Python :: 3.9
Classifier: Programming Language :: Python :: 3.10
Classifier: Programming Language :: Python :: 3.11
Requires-Python: >=3.7
License-File: LICENSE
Requires-Dist: requests >=2.31.0
Requires-Dist: rich >=13.7.1
Requires-Dist: fake-useragent >=1.5.0
